TextClassifier/__init__.py
TextClassifier-0.0.4.dist-info/DESCRIPTION.rst
TextClassifier-0.0.4.dist-info/METADATA
TextClassifier-0.0.4.dist-info/RECORD
TextClassifier-0.0.4.dist-info/WHEEL
TextClassifier-0.0.4.dist-info/metadata.json
TextClassifier-0.0.4.dist-info/top_level.txt
