Metadata-Version: 2.0
Name: TextClassifier
Version: 0.0.4
Summary: Short text Classifier based on Numpy,scikit-learn,Pandas,Matplotlib
Home-page: https://github.com/ArnoldGaius/Text_Classifier
Author: Arnold_Gaius,ChiangClaire
Author-email: jiangcmd@qq.com
License: MIT
Platform: UNKNOWN
Classifier: Programming Language :: Python
Classifier: Programming Language :: Python :: 2
Classifier: Programming Language :: Python :: 2.7
Requires-Dist: matplotlib
Requires-Dist: numpy
Requires-Dist: pandas
Requires-Dist: scikit-learn
